lastmile_eval/utils.py
lastmile_eval/api/__init__.py
lastmile_eval/api/auth_config.py
lastmile_eval/api/evaluations.py
lastmile_eval/common/__init__.py
lastmile_eval/common/types.py
lastmile_eval/common/utils.py
lastmile_eval/examples/rag.py
lastmile_eval/examples/text.py
lastmile_eval/examples/rag_debugger/run_llm.py
lastmile_eval/examples/rag_debugger/tracing/tracing.py
lastmile_eval/rag/__init__.py
lastmile_eval/rag/debugger/__init__.py
lastmile_eval/rag/debugger/app.py
lastmile_eval/rag/debugger/app_utils.py
lastmile_eval/rag/debugger/server.py
lastmile_eval/rag/debugger/api/__init__.py
lastmile_eval/rag/debugger/api/add_rag_event_interface.py
lastmile_eval/rag/debugger/api/evaluation.py
lastmile_eval/rag/debugger/api/manage_params_interface.py
lastmile_eval/rag/debugger/api/tracing.py
lastmile_eval/rag/debugger/client/build/asset-manifest.json
lastmile_eval/rag/debugger/client/build/index.html
lastmile_eval/rag/debugger/client/build/manifest.json
lastmile_eval/rag/debugger/client/build/robots.txt
lastmile_eval/rag/debugger/client/build/static/css/main.c0f29cce.css
lastmile_eval/rag/debugger/client/build/static/css/main.c0f29cce.css.map
lastmile_eval/rag/debugger/client/build/static/js/2.664b25cd.chunk.js
lastmile_eval/rag/debugger/client/build/static/js/2.664b25cd.chunk.js.map
lastmile_eval/rag/debugger/client/build/static/js/732.c19b7ab1.chunk.js
lastmile_eval/rag/debugger/client/build/static/js/732.c19b7ab1.chunk.js.map
lastmile_eval/rag/debugger/client/build/static/js/821.cb385427.chunk.js
lastmile_eval/rag/debugger/client/build/static/js/821.cb385427.chunk.js.map
lastmile_eval/rag/debugger/client/build/static/js/main.fba7430e.js
lastmile_eval/rag/debugger/client/build/static/js/main.fba7430e.js.LICENSE.txt
lastmile_eval/rag/debugger/client/build/static/js/main.fba7430e.js.map
lastmile_eval/rag/debugger/common/core.py
lastmile_eval/rag/debugger/common/general_functional_utils.py
lastmile_eval/rag/debugger/common/types.py
lastmile_eval-0.0.81.dist-info/LICENSE
lastmile_eval-0.0.81.dist-info/METADATA
lastmile_eval-0.0.81.dist-info/WHEEL
lastmile_eval-0.0.81.dist-info/entry_points.txt
lastmile_eval-0.0.81.dist-info/top_level.txt
lastmile_eval-0.0.81.dist-info/RECORD
