Metadata-Version: 2.1
Name: lastmile-eval
Version: 0.0.81
Summary: An API to measure evaluation criteria (ex: faithfulness) of generative AI outputs
Author: LastMile AI
Project-URL: Homepage, https://github.com/lastmile-ai/eval
Project-URL: Bug Tracker, https://github.com/lastmile-ai/eval/issues
Classifier: Intended Audience :: Developers
Classifier: Programming Language :: Python :: 3
Requires-Python: >=3.10
License-File: LICENSE
Requires-Dist: requests
Requires-Dist: python-dotenv
Requires-Dist: pydantic>=2.1
Requires-Dist: result
Requires-Dist: lastmile-utils
Requires-Dist: evaluate>=0.4.1
Requires-Dist: numpy<2.0.0
Requires-Dist: arize-phoenix-evals>=0.5.0
Requires-Dist: pandas>=2.1.2
Requires-Dist: instructor
Requires-Dist: openai>=1.0.0
Requires-Dist: rouge-score
Requires-Dist: opentelemetry-api
Requires-Dist: opentelemetry-sdk
Requires-Dist: opentelemetry-exporter-otlp
Requires-Dist: opentelemetry-semantic-conventions
Requires-Dist: openinference-semantic-conventions
Requires-Dist: packaging
Requires-Dist: proto-plus>=1.24.0
Provides-Extra: ui
Requires-Dist: fastapi==0.110.1; extra == "ui"
Requires-Dist: jinja2; extra == "ui"
Requires-Dist: uvicorn; extra == "ui"
Requires-Dist: email-validator==2.1.1; extra == "ui"
Requires-Dist: python-aiconfig>=1.1.34; extra == "ui"
